[{"__type__":"cc.SceneAsset","_name":"main","scene":{"__id__":1},"asyncLoadAssets":null},{"__type__":"cc.Scene","_name":"New Node","_children":[{"__id__":2}],"_anchorPoint":{"__type__":"cc.Vec2"},"_scale":{"__type__":"cc.Vec3","x":0.6129668563845001,"y":0.6129668563845001,"z":1},"autoReleaseAssets":false},{"__type__":"cc.Node","_name":"Canvas","_parent":{"__id__":1},"_children":[{"__id__":3},{"__id__":4}],"_components":[{"__type__":"cc.Canvas","node":{"__id__":2},"_designResolution":{"__type__":"cc.Size","width":1200,"height":640}}],"_color":{"__type__":"cc.Color","r":252,"g":252,"b":252},"_contentSize":{"__type__":"cc.Size","width":1200,"height":640},"_position":{"__type__":"cc.Vec3","x":600,"y":320},"_scale":{"__type__":"cc.Vec3","x":1,"y":1,"z":1},"_id":"a286bbGknJLZpRpxROV6M94"},{"__type__":"cc.Node","_name":"Main Camera","_parent":{"__id__":2},"_level":1,"_components":[{"__type__":"cc.Camera","node":{"__id__":3},"_clearFlags":7,"_depth":-1}],"_scale":{"__type__":"cc.Vec3","x":1,"y":1,"z":1}},{"__type__":"cc.Node","_name":"chart","_parent":{"__id__":2},"_level":1,"_components":[{"__type__":"b6119lwZ29EIKgiT3thReHB","node":{"__id__":4},"rect":{"__type__":"cc.Rect","x":-400,"y":-200,"width":800,"height":400},"rowCount":10,"columnCount":15}],"_scale":{"__type__":"cc.Vec3","x":1,"y":1,"z":1}}]